rtl/fix_point_adder.sv
`timescale 1us/1ns

module fix_point_adder
    #(
        parameter Q = 13,   // Fractional
        parameter N = 16 
    )
    (
        input          clk,
        input          rstn,
        input    [N-1:0] a,
        input    [N-1:0] b,
        output  [N-1:0] sum
    );

reg [N-1:0] r_sum;

always @(posedge clk or negedge rstn) begin
    if(!rstn) begin 
        r_sum = 'b0;
    end
    // If both numbers are of same sign
    else if(a[N-1] == b[N-1]) begin 
        r_sum[N-2:0] = a[N-2:0] + b[N-2:0]; // Since they have the same sign, absolute sum increases
        r_sum[N-1] = a[N-1];
    end
    
    // a > 0 and b < 0
    else if(a[N-1] == 0 && b[N-1] == 1) begin  // a - b
        //  If a > b
        if(a[N-2:0] > b[N-2:0]) begin 
            r_sum[N-2:0] = a[N-2:0] - b[N-2:0]; 
            r_sum[N-1] = 0; // Final answer is positive
        end
        else begin // a < b 
            r_sum[N-2:0] = b[N-2:0] - a[N-2:0]; 
            if(r_sum[N-2:0] == 0)
                r_sum[N-1] = 0; // The zero case
            else
                r_sum[N-1] = 1; // Final answer is negative
        end
    end

    // a < 0 and b > 0
    else if(a[N-1] == 1 && b[N-1] == 0) begin  // b - a
        //  If b > a
        if(b[N-2:0] > a[N-2:0]) begin 
            r_sum[N-2:0] = b[N-2:0] - a[N-2:0]; 
            r_sum[N-1] = 0; // Final answer is positive
        end
        else begin // a > b 
            r_sum[N-2:0] = a[N-2:0] - b[N-2:0]; 
            if(r_sum[N-2:0] == 0)
                r_sum[N-1] = 0; // The zero case
            else
                r_sum[N-1] = 1; // Final answer is negative
        end
    end

end

// Final result
assign sum = r_sum;

initial begin
    $dumpfile("dump.vcd");
    $dumpvars(1, fix_point_adder);
  end

endmodule

rtl/dump.vcd
$date
	Sat Sep 30 10:39:58 2023
$end
$version
	Icarus Verilog
$end
$timescale
	1ps
$end
$scope module fix_point_adder $end
$var wire 16 ! a [15:0] $end
$var wire 16 " b [15:0] $end
$var wire 1 # clk $end
$var wire 1 $ rstn $end
$var wire 16 % sum [15:0] $end
$var reg 16 & r_sum [15:0] $end
$upscope $end
$enddefinitions $end
#0
$dumpvars
bx &
bx %
z$
1#
bz "
bz !
$end
#5000
0#
#10000
1#
#15000
0#
#20000
1#
#25000
0#
#30000
1#
#35000
0#
#40000
1#
#45000
0#
#50000
1#
#55000
0#
#60000
1#
#65000
0#
#70000
1#
#75000
0#
#80000
1#
#85000
0#
#90000
b0 %
b0 &
0$
1#
#95000
0#
#100000
1#
#105000
0#
#110000
1#
#115000
0#
#120000
1#
#125000
0#
#130000
1#
#135000
0#
#140000
1$
1#
#145000
0#
#150000
1#
#155000
0#
#160000
1#
#165000
0#
#170000
1#
#175000
0#
#180000
1#
#185000
0#
#190000
1#
#195000
0#
#200000
b10100000000000 "
b101000000000000 !
1#
#205000
0#
#210000
b111100000000000 %
b111100000000000 &
1#
#215000
0#
#220000
1#
#225000
0#
#230000
b1101000000000000 !
1#
#235000
0#
#240000
b1010100000000000 %
b1010100000000000 &
1#
#245000
0#
#250000
1#
#255000
0#
#260000
b1010100000000000 "
b101000000000000 !
1#
#265000
0#
#270000
b10100000000000 %
b10100000000000 &
1#
#275000
0#
#280000
1#
#285000
0#
#290000
b1101000000000000 !
1#
#295000
0#
#300000
b1111100000000000 %
b1111100000000000 &
1#
